odoo8_addon_partner_contact_personal_information_page-8.0.1.0.0.99.dev5-py2.7-nspkg.pth
odoo8_addon_partner_contact_personal_information_page-8.0.1.0.0.99.dev5.dist-info/METADATA
odoo8_addon_partner_contact_personal_information_page-8.0.1.0.0.99.dev5.dist-info/RECORD
odoo8_addon_partner_contact_personal_information_page-8.0.1.0.0.99.dev5.dist-info/WHEEL
odoo8_addon_partner_contact_personal_information_page-8.0.1.0.0.99.dev5.dist-info/namespace_packages.txt
odoo8_addon_partner_contact_personal_information_page-8.0.1.0.0.99.dev5.dist-info/top_level.txt
odoo_addons/partner_contact_personal_information_page/README.rst
odoo_addons/partner_contact_personal_information_page/__init__.py
odoo_addons/partner_contact_personal_information_page/__openerp__.py
odoo_addons/partner_contact_personal_information_page/i18n/de.po
odoo_addons/partner_contact_personal_information_page/i18n/es.po
odoo_addons/partner_contact_personal_information_page/i18n/fr.po
odoo_addons/partner_contact_personal_information_page/i18n/it.po
odoo_addons/partner_contact_personal_information_page/i18n/nl.po
odoo_addons/partner_contact_personal_information_page/i18n/partner_contact_personal_information_page.pot
odoo_addons/partner_contact_personal_information_page/i18n/sl.po
odoo_addons/partner_contact_personal_information_page/static/description/icon.png
odoo_addons/partner_contact_personal_information_page/views/res_partner.xml
